qiskit_rigetti/__init__.py
qiskit_rigetti/_qcs_backend.py
qiskit_rigetti/_qcs_job.py
qiskit_rigetti/_qcs_provider.py
qiskit_rigetti/_quil_circuit.py
qiskit_rigetti/gates/__init__.py
qiskit_rigetti/gates/_can.py
qiskit_rigetti/gates/_cphase.py
qiskit_rigetti/gates/_pswap.py
qiskit_rigetti/gates/_xy.py
qiskit_rigetti/hooks/__init__.py
qiskit_rigetti/hooks/pre_compilation.py
qiskit_rigetti/hooks/pre_execution.py
qiskit_rigetti/py.typed
qiskit_rigetti-0.4.7.dist-info/LICENSE
qiskit_rigetti-0.4.7.dist-info/METADATA
qiskit_rigetti-0.4.7.dist-info/WHEEL
qiskit_rigetti-0.4.7.dist-info/RECORD
