Metadata-Version: 2.1
Name: qiskit-rigetti
Version: 0.4.7
Summary: Provider for running Qiskit circuits on Rigetti QPUs and simulators.
Home-page: https://github.com/rigetti/qiskit-rigetti
License: Apache-2.0
Keywords: Qiskit,Quil,Rigetti,pyQuil,Quantum
Author: Rigetti Computing
Requires-Python: >=3.8,<3.12
Classifier: Development Status :: 4 - Beta
Classifier: Intended Audience :: Developers
Classifier: Intended Audience :: Science/Research
Classifier: License :: OSI Approved :: Apache Software License
Classifier: Programming Language :: Other
Classifier: Programming Language :: Python :: 3
Classifier: Programming Language :: Python :: 3.8
Classifier: Programming Language :: Python :: 3.9
Classifier: Programming Language :: Python :: 3.10
Classifier: Programming Language :: Python :: 3.11
Classifier: Topic :: Scientific/Engineering :: Physics
Classifier: Typing :: Typed
Provides-Extra: docs
Requires-Dist: furo ; extra == "docs"
Requires-Dist: importlib_metadata ; python_version < "3.8"
Requires-Dist: ipython (>=7.25.0,<8.0.0) ; extra == "docs"
Requires-Dist: myst-parser (>=0.17.0,<0.18.0) ; extra == "docs"
Requires-Dist: nbsphinx (>=0.8.6,<0.9.0) ; extra == "docs"
Requires-Dist: numpy (>=1.23.3,<2.0.0)
Requires-Dist: pyquil (>=4.0.0,<5.0.0)
Requires-Dist: qiskit (>=0.38.0)
Requires-Dist: sphinx (>=4.1.1,<5.0.0) ; extra == "docs"
Requires-Dist: sphinx-autoapi (>=1.8.1,<2.0.0) ; extra == "docs"
Requires-Dist: sphinx-autobuild (>=2021.3.14,<2022.0.0) ; extra == "docs"
Project-URL: Documentation, https://qiskit-rigetti.readthedocs.io
Project-URL: Repository, https://github.com/rigetti/qiskit-rigetti
